rdclient/__init__.py
rdclient/main.py
rdclient/rd
rd-1.6.0.0.dist-info/METADATA
rd-1.6.0.0.dist-info/WHEEL
rd-1.6.0.0.dist-info/entry_points.txt
rd-1.6.0.0.dist-info/top_level.txt
rd-1.6.0.0.dist-info/RECORD
