Metadata-Version: 2.1
Name: rd
Version: 1.6.0.0
Summary: reliable-download client tool
Home-page: https://gitlab.emacsos.com/sylecn/reliable-download
Download-URL: https://pypi.org/project/rd/
Author: Yuanle Song
Author-email: sylecn@gmail.com
Maintainer: Yuanle Song
Maintainer-email: sylecn@gmail.com
License: GPLv3+
Classifier: Development Status :: 5 - Production/Stable
Classifier: Intended Audience :: End Users/Desktop
Classifier: Intended Audience :: System Administrators
Classifier: License :: OSI Approved :: GNU General Public License v3 or later (GPLv3+)
Classifier: Operating System :: POSIX :: Linux
Classifier: Topic :: System :: Networking
Classifier: Programming Language :: Haskell
Classifier: Programming Language :: Python :: 2.7
Classifier: Programming Language :: Python :: 3.4
Classifier: Programming Language :: Python :: 3.5
Classifier: Programming Language :: Python :: 3.6
Classifier: Programming Language :: Python :: 3.7
Classifier: Programming Language :: Python :: 3.8
Classifier: Programming Language :: Python :: 3.9
